dictionary/__init__.py
dictionary/dictionary.py
aybala_cs453_dictionary-2.0.0.dist-info/METADATA
aybala_cs453_dictionary-2.0.0.dist-info/WHEEL
aybala_cs453_dictionary-2.0.0.dist-info/top_level.txt
aybala_cs453_dictionary-2.0.0.dist-info/RECORD
