Metadata-Version: 2.1
Name: aybala-cs453-dictionary
Version: 2.0.0
Summary: UNKNOWN
Author: Aybala Karakaya
License: UNKNOWN
Platform: UNKNOWN
Requires-Python: >=3.8
Requires-Dist: requests (>=2.23.0)
